Workbook
Name salario: 'Configuracoes'!$B$3
Name taxa_mensal: 'Configuracoes'!$B$4
Name percentual_sugerido: 'Configuracoes'!$B$5
Name prazo_anos: 'Configuracoes'!$B$6
Name aporte: 'Configuracoes'!$B$7
Name aporte_sugerido: 'Configuracoes'!$B$3*'Configuracoes'!$B$5

Sheet Simulador
A1: FIIS EM FOCO | SIMULADOR DE INVESTIMENTOS
A2: Simulação educacional: estimativas hipotéticas, não promessa de rentabilidade.
A4: ENTRADAS DA SIMULAÇÃO | D4: RESULTADOS PRINCIPAIS
A5: Aporte mensal (R$) | B5: =aporte | D5: Patrimônio estimado | E5: =-FV(B7,B6*12,B5,0,0)
A6: Prazo (anos) | B6: =prazo_anos | D6: Dividendos mensais estimados | E6: =E5*B7
A7: Rendimento mensal | B7: =taxa_mensal | D7: Aporte sugerido (30% do salário) | E7: =aporte_sugerido
A8: Perfil do investidor | B8: Moderado | D8: Patrimônio com aporte sugerido | E8: =-FV(taxa_mensal,prazo_anos*12,aporte_sugerido,0,0)
A11: PROJEÇÃO DE PATRIMÔNIO POR PRAZO | D11: DIVISÃO DO APORTE POR TIPO DE FII
A12: Prazo (anos) | B12: Meses | C12: Patrimônio estimado (R$) | D12: Tipo de fundo | E12: Percentual | F12: Aporte alocado (R$)
A13: 2 | B13: =A13*12 | C13: =-FV($B$7,B13,$B$5,0,0) | D13: Tijolo | E13: =VLOOKUP($B$8&"|"&D13,Distribuicao!$A$3:$C$20,3,FALSE) | F13: =E13*$B$5
A14: 5 | B14: =A14*12 | C14: =-FV($B$7,B14,$B$5,0,0) | D14: Papel | E14: =VLOOKUP($B$8&"|"&D14,Distribuicao!$A$3:$C$20,3,FALSE) | F14: =E14*$B$5
A15: 10 | B15: =A15*12 | C15: =-FV($B$7,B15,$B$5,0,0) | D15: Híbridos | E15: =VLOOKUP($B$8&"|"&D15,Distribuicao!$A$3:$C$20,3,FALSE) | F15: =E15*$B$5
A16: 20 | B16: =A16*12 | C16: =-FV($B$7,B16,$B$5,0,0) | D16: Fundos de fundos (FOFs) | E16: =VLOOKUP($B$8&"|"&D16,Distribuicao!$A$3:$C$20,3,FALSE) | F16: =E16*$B$5
A17: 30 | B17: =A17*12 | C17: =-FV($B$7,B17,$B$5,0,0) | D17: Desenvolvimento | E17: =VLOOKUP($B$8&"|"&D17,Distribuicao!$A$3:$C$20,3,FALSE) | F17: =E17*$B$5
D18: Logística | E18: =VLOOKUP($B$8&"|"&D18,Distribuicao!$A$3:$C$20,3,FALSE) | F18: =E18*$B$5
A19: Nota: a VF considera aportes no fim de cada mês (tipo 0).
D20: Como interpretar
D21: 1. Altere os valores na aba Configuracoes.
D22: 2. Escolha um perfil na célula B8.
D23: 3. Confira a divisão do aporte e o gráfico.
D24: 4. Todos os valores são exemplos didáticos, não recomendação financeira.

Sheet Configuracoes
A1: CONFIGURAÇÕES DA SIMULAÇÃO
A2: Parâmetro | B2: Valor de exemplo | C2: Descrição | D2: Observação
A3: Salário mensal | B3: 5000 | C3: Renda mensal usada para calcular a sugestão de aporte. | D3: Valor fictício
A4: Taxa de rendimento mensal | B4: 0.008 | C4: Taxa hipotética usada na simulação. | D4: 0,8% ao mês; não é garantia
A5: Percentual sugerido do salário | B5: 0.3 | C5: Percentual usado na simulação alternativa. | D5: Sugestão didática
A6: Prazo em anos | B6: 10 | C6: Prazo principal da simulação. | D6: Entre 2 e 30 anos
A7: Aporte mensal informado | B7: 500 | C7: Valor escolhido para investir por mês. | D7: Valor fictício
A9: Nota: | B9: Valores fictícios para demonstração. Rentabilidade e dividendos não são garantidos.

Sheet Distribuicao
A1: TABELA DE APOIO — PERFIL × TIPO DE FII
A2: Chave composta | B2: Tipo de fundo | C2: Percentual | E2: Perfis | G2: Conferência dos percentuais | J2: Sobre os percentuais
A3: Conservador|Tijolo | B3: Tijolo | C3: 0.15 | E3: Conservador | G3: Perfil | H3: Total | J3: Distribuições ilustrativas criadas para o projeto acadêmico. Não são recomendação de investimento.
A4: Conservador|Papel | B4: Papel | C4: 0.35 | E4: Moderado | G4: Conservador | H4: =SUMIF($A$3:$A$20,G4&"|*",$C$3:$C$20)
A5: Conservador|Híbridos | B5: Híbridos | C5: 0.2 | E5: Arrojado | G5: Moderado | H5: =SUMIF($A$3:$A$20,G5&"|*",$C$3:$C$20)
A6: Conservador|Fundos de fundos (FOFs) | B6: Fundos de fundos (FOFs) | C6: 0.15 | G6: Arrojado | H6: =SUMIF($A$3:$A$20,G6&"|*",$C$3:$C$20)
A7: Conservador|Desenvolvimento | B7: Desenvolvimento | C7: 0.05
A8: Conservador|Logística | B8: Logística | C8: 0.1
A9: Moderado|Tijolo | B9: Tijolo | C9: 0.25
A10: Moderado|Papel | B10: Papel | C10: 0.25
A11: Moderado|Híbridos | B11: Híbridos | C11: 0.15
A12: Moderado|Fundos de fundos (FOFs) | B12: Fundos de fundos (FOFs) | C12: 0.15
A13: Moderado|Desenvolvimento | B13: Desenvolvimento | C13: 0.1
A14: Moderado|Logística | B14: Logística | C14: 0.1
A15: Arrojado|Tijolo | B15: Tijolo | C15: 0.35
A16: Arrojado|Papel | B16: Papel | C16: 0.15
A17: Arrojado|Híbridos | B17: Híbridos | C17: 0.15
A18: Arrojado|Fundos de fundos (FOFs) | B18: Fundos de fundos (FOFs) | C18: 0.1
... A20: Arrojado|Logística | B20: Logística | C20: 0.1
